src/melon-analytics_pricing/__init__.py
src/melon-analytics_pricing/neighbors.py
melon_analytics_pricing-0.0.1.dist-info/METADATA
melon_analytics_pricing-0.0.1.dist-info/WHEEL
melon_analytics_pricing-0.0.1.dist-info/licenses/LICENSE
melon_analytics_pricing-0.0.1.dist-info/RECORD
