Metadata-Version: 2.1
Name: melon-analytics_pricing
Version: 0.0.1
Summary: Script for apartment price benchmarking based on market data
Author-email: eMonitor AG <christoph.puetz@emonitor.ch>
License-File: LICENSE
Classifier: Operating System :: OS Independent
Classifier: Programming Language :: Python :: 3
Requires-Python: >=3.7
